textcolor/__init__.py
textcolor/all.py
textcolor/text.py
textcolor/version.py
textcolor_v2-0.0.1.dist-info/METADATA
textcolor_v2-0.0.1.dist-info/WHEEL
textcolor_v2-0.0.1.dist-info/top_level.txt
textcolor_v2-0.0.1.dist-info/RECORD
