Metadata-Version: 2.4
Name: textcolor_v2
Version: 0.0.1
Summary: Use textcolor to have custom colors
Author-email: SH_Dev <glock.96.beamed@gmail.com>
Requires-Python: >=3.7
Dynamic: requires-python
